pystand.py
pystand-2.27.dist-info/METADATA
pystand-2.27.dist-info/WHEEL
pystand-2.27.dist-info/entry_points.txt
pystand-2.27.dist-info/top_level.txt
pystand-2.27.dist-info/RECORD
