Metadata-Version: 2.4
Name: pystand
Version: 2.27
Summary: Install Python versions from python-build-standalone project
Author-email: Mark Blakeney <mark.blakeney@bullet-systems.net>
License-Expression: GPL-3.0-or-later
Project-URL: Homepage, https://github.com/bulletmark/pystand
Keywords: python-build-standalone,pyenv,hatch,pdm
Classifier: Programming Language :: Python :: 3
Requires-Python: >=3.8
Requires-Dist: argcomplete
Requires-Dist: packaging
Requires-Dist: platformdirs
Requires-Dist: argparse-from-file
Requires-Dist: pygithub
Requires-Dist: certifi
Requires-Dist: filelock
Requires-Dist: zstandard; python_version < "3.14"
